<?xml version="1.0" encoding="UTF-8"?>
<odoo>
    <data>

        <record id="mechanical_ggbs_form" model="ir.ui.view">
        <field name="name">mechanical.ggbs.form</field>
        <field name="model">mechanical.ggbs</field>
        <field name="arch" type="xml">
            <form>
                <sheet>
                <group >
                        <h1>
                            <field name="name" readonly="1" nolabel="1"/>
                        </h1>
                    </group>
                    <group>
                        <field name="srf_id" invisible="1"/>
                        <field name="sample_id" />
                        <field name="eln_ref"/>
                        <field name="parameter_id" invisible="1"/>
                    </group>
                    <group>
                      <field name="sample_parameters">
                        <tree>
                          <field name="parameter_name"/>
                          <field name="test_method"/>
                        </tree>
                      </field>
                    </group>
                    
                    <!-- Normal Consistency Start -->
                    
                    <group >
                        <field name="tests" widget="many2many_tags" options="{'no_create':True,'no_open': True}"/>
                    </group>
                    <group attrs="{'invisible': [('normal_consistency_visible', '=', False)]}">
                        <h1>
                            <field name="normal_consistency_name" readonly="1" nolabel="1"/>
                            <field name="normal_consistency_visible" invisible="1"/>
                        </h1>
                    </group>
                    
                    <group attrs="{'invisible': [('normal_consistency_visible', '=', False)]}">
                        
                        <label for="wt_of_cement_trial1" string="Wt. of Cement(g)" />
                        <div class="address_format " >
                          <group colspan="1"  class="oe_inline">
                            <label for="wt_of_cement_trial1" string="Trial 1" />
                            <field  name="wt_of_cement_trial1"  colspan="3"  nolabel="1"/>
                          </group>
                          
                        </div>
                    </group>
                    <group attrs="{'invisible': [('normal_consistency_visible', '=', False)]}">
                        
                        
                          <group >
                            <!-- <label for="wt_of_ggbs_trial1" string="Trial 1" /> -->
                            <field  name="wt_of_ggbs_trial1"  colspan="3" />
                          </group>
                          
                    </group>
                    <group attrs="{'invisible': [('normal_consistency_visible', '=', False)]}">
                        
                          <group >
                            <!-- <label for="total_wt_sample" string="Trial 1" /> -->
                            <field  name="total_wt_sample"  colspan="3"/>
                          </group>
                          
                        
                    </group>
                    <group attrs="{'invisible': [('normal_consistency_visible', '=', False)]}">
                       
                          <group >
                            <field  name="wt_water_req"  colspan="3"  />
                          </group>
                          
                    </group>
                    <group attrs="{'invisible': [('normal_consistency_visible', '=', False)]}">
                        
                          <group >
                            
                            <field  name="penetration_vicat"  colspan="3"  />
                          </group>
                         
                    </group>
                    <group attrs="{'invisible': [('normal_consistency_visible', '=', False)]}">
                        
                          <group >
                            <field  name="normal_consistency"  colspan="3"  />
                          </group>
                          
                    </group>


                    <!-- Normal Consistency Cement  -->
                    <group attrs="{'invisible': [('normal_consistency_cement_visible', '=', False)]}">
                        <h1>
                            <field name="normal_consistency_cement_name" readonly="1" nolabel="1"/>
                            <field name="normal_consistency_cement_visible" invisible="1"/>
                        </h1>
                    </group>

                    <group attrs="{'invisible': [('normal_consistency_cement_visible', '=', False)]}">
                        
                        <label for="wt_cement" string="Wt. of Cement(g)" />
                        <div class="address_format " >
                          <group colspan="1"  class="oe_inline">
                            <label for="wt_cement" string="Trial 1" />
                            <field  name="wt_cement"  colspan="3"  nolabel="1"/>
                          </group>
                          
                        </div>
                    </group>
                    
                   
                    <group attrs="{'invisible': [('normal_consistency_cement_visible', '=', False)]}">
                       
                          <group >
                            <field  name="wt_water_req_cement"  colspan="3"  />
                          </group>
                          
                    </group>
                    <group attrs="{'invisible': [('normal_consistency_cement_visible', '=', False)]}">
                        
                          <group >
                            
                            <field  name="penetration_vicat_cement"  colspan="3"  />
                          </group>
                         
                    </group>
                    <group attrs="{'invisible': [('normal_consistency_cement_visible', '=', False)]}">
                        
                          <group >
                            <field  name="normal_consistency_cement"  colspan="3"  />
                          </group>
                          
                    </group>


                    <!-- Specific Gravity -->
                    <group attrs="{'invisible': [('specific_gravity_visible', '=', False)]}">
                        <h1>
                            <field name="specific_gravity_name" readonly="1" nolabel="1"/>
                            <field name="specific_gravity_visible" invisible="1"/>
                        </h1>
                    </group>
                    
                    
                    <group attrs="{'invisible': [('specific_gravity_visible', '=', False)]}">
                        <label for="wt_of_ggbs_trial1" string="Wt. of GGBS(g)" />
                        <div class="address_format " >
                          <group colspan="1"  class="oe_inline">
                            <label for="wt_of_ggbs_sg_trial1" string="Trial 1" />
                            <field  name="wt_of_ggbs_sg_trial1"  colspan="3"  nolabel="1"/>
                          </group>
                          <group colspan="1" class="oe_inline"  >
                            <label for="wt_of_ggbs_sg_trial2" string="Trial 2" />
                            <field  name="wt_of_ggbs_sg_trial2"  colspan="3"  nolabel="1"/>
                          </group>
                        </div>
                    </group>
                    <group attrs="{'invisible': [('specific_gravity_visible', '=', False)]}">
                        <label for="initial_volume_kerosine_trial1" string="Initial Volume of kerosine (ml)V1" />
                        <div class="address_format " >
                          <group colspan="1"  class="oe_inline">
                            <label for="initial_volume_kerosine_trial1" string="" />
                            <field  name="initial_volume_kerosine_trial1"  colspan="3"  nolabel="1"/>
                          </group>
                          <group colspan="1" class="oe_inline"  >
                            <label for="initial_volume_kerosine_trial2" string="" />
                            <field  name="initial_volume_kerosine_trial2"  colspan="3"  nolabel="1"/>
                          </group>
                        </div>
                    </group>
                    <group attrs="{'invisible': [('specific_gravity_visible', '=', False)]}">
                        <label for="final_volume_kerosine_trial1" string="Final Volume of kerosine and Cement (After immersion in constant water bath)(ml) V2" />
                        <div class="address_format " >
                          <group colspan="1"  class="oe_inline">
                            <label for="final_volume_kerosine_trial1" string="" />
                            <field  name="final_volume_kerosine_trial1"  colspan="3"  nolabel="1"/>
                          </group>
                          <group colspan="1" class="oe_inline"  >
                            <label for="final_volume_kerosine_trial2" string="" />
                            <field  name="final_volume_kerosine_trial2"  colspan="3"  nolabel="1"/>
                          </group>
                        </div>
                    </group>
                    <group attrs="{'invisible': [('specific_gravity_visible', '=', False)]}">
                        <label for="displaced_volume_trial1" string="Displaced volume (cm³)" />
                        <div class="address_format " >
                          <group colspan="1"  class="oe_inline">
                            <label for="displaced_volume_trial1" string="" />
                            <field  name="displaced_volume_trial1"  colspan="3"  nolabel="1"/>
                          </group>
                          <group colspan="1" class="oe_inline"  >
                            <label for="displaced_volume_trial2" string="" />
                            <field  name="displaced_volume_trial2"  colspan="3"  nolabel="1"/>
                          </group>
                        </div>
                    </group>

                    <group attrs="{'invisible': [('specific_gravity_visible', '=', False)]}">
                        <label for="specific_gravity_trial1" string="Specific Gravity" />
                        <div class="address_format " >
                          <group colspan="1"  class="oe_inline">
                            <label for="specific_gravity_trial1" string="" />
                            <field  name="specific_gravity_trial1"  colspan="3"  nolabel="1"/>
                          </group>
                          <group colspan="1" class="oe_inline"  >
                            <label for="specific_gravity_trial1" string="" />
                            <field  name="specific_gravity_trial1"  colspan="3"  nolabel="1"/>
                          </group>
                        </div>
                    </group>
                    
                    <group attrs="{'invisible': [('specific_gravity_visible', '=', False)]}">
                      <field name="average_specific_gravity" string="Average"/>
                    </group>

                    <!-- Slag index  -->
                    <group attrs="{'invisible': [('slag_activity_visible', '=', False)]}">
                        <h1>
                            <field name="slag_activity_name" readonly="1" nolabel="1"/>
                            <field name="slag_activity_visible" invisible="1"/>
                        </h1>
                    </group>
                    <group attrs="{'invisible': [('slag_activity_visible', '=', False)]}" style="width:40%">
                      <field  name="wt_of_cement_slag"  colspan="3" />
                      <field  name="wt_of_ggbs_slag"  colspan="3" />
                      <field  name="wt_of_standard_sand_grade1"  colspan="3" />
                      <field  name="wt_of_standard_sand_grade2"  colspan="3" />
                      <field  name="wt_of_standard_sand_grade1"  colspan="3" />
                      <field  name="total_weight_sand"  colspan="3" />
                      <field  name="quantity_of_water"  colspan="3" />
                    </group>
                    
                    <!-- 7 days  -->

                    <group attrs="{'invisible': [('slag_activity_visible', '=', False)]}">
                        <h1>
                            <field name="casting_7_name" readonly="1" nolabel="1"/>

                            <!-- <field name="dry_sieving_visible" invisible="1"/> -->
                        </h1>
                    </group>
                    <group attrs="{'invisible': [('slag_activity_visible', '=', False)]}">
                            <field name="status_7days"/>
                      
                    </group>
                    
                    <group attrs="{'invisible': [('slag_activity_visible', '=', False)]}">


                      <field name="casting_date_7days"/>
                      <field name="testing_date_7days"/>
                      
                      <field name="slag_7days_table">
                        <tree editable="bottom">
                          <field name="length"/>
                          <field name="width"/>
                          <field name="crosssectional_area"/>
                          <field name="wt_of_cement_cube"/>
                          <field name="crushing_load" />
                          <field name="compressive_strength" />
                        </tree>
                      </field>
                      <field name="average_7days_slag"/>
                    </group>

                    <!-- 28 days  -->
                    <group attrs="{'invisible': [('slag_activity_visible', '=', False)]}">
                        <h1>
                            <field name="casting_28_name" readonly="1" nolabel="1"/>

                            <!-- <field name="dry_sieving_visible" invisible="1"/> -->
                        </h1>
                    </group>
                    <group attrs="{'invisible': [('slag_activity_visible', '=', False)]}">
                            <field name="status_28days"/>
                      
                    </group>
                    
                    <group attrs="{'invisible': [('slag_activity_visible', '=', False)]}">


                      <field name="casting_date_28days"/>
                      <field name="testing_date_28days"/>
                      
                      <field name="slag_28days_table">
                        <tree editable="bottom">
                          <field name="length"/>
                          <field name="width"/>
                          <field name="crosssectional_area"/>
                          <field name="wt_of_cement_cube"/>
                          <field name="crushing_load" />
                          <field name="compressive_strength" />
                        </tree>
                      </field>
                      <field name="average_28days_slag"/>
                    </group>

                    <!-- opc cube  -->
                    <group attrs="{'invisible': [('slag_activity_visible', '=', False)]}">
                      <h5>Compressive Strength of the control OPC mortar cube</h5>
                    </group>
                    <group attrs="{'invisible': [('slag_activity_visible', '=', False)]}" style="width:40%">
                      <field  name="wt_of_cement_slag_opc"  colspan="3" />
                      <field  name="wt_of_standard_sand_grade1_opc"  colspan="3" />
                      <field  name="wt_of_standard_sand_grade2_opc"  colspan="3" />
                      <field  name="wt_of_standard_sand_grade1"  colspan="3" />
                      <field  name="total_weight_sand_opc"  colspan="3" />
                      <field  name="quantity_of_water_opc"  colspan="3" />

                    </group>

                    <!-- 7 days  -->

                    <group attrs="{'invisible': [('slag_activity_visible', '=', False)]}">
                        <h1>
                            <field name="casting_7_name_opc" readonly="1" nolabel="1"/>

                            <!-- <field name="dry_sieving_visible" invisible="1"/> -->
                        </h1>
                    </group>
                    <group attrs="{'invisible': [('slag_activity_visible', '=', False)]}">
                            <field name="status_7days_opc"/>
                      
                    </group>
                    
                    <group attrs="{'invisible': [('slag_activity_visible', '=', False)]}">


                      <field name="casting_date_7days_opc"/>
                      <field name="testing_date_7days_opc"/>
                      
                      <field name="slag_7days_table_opc">
                        <tree editable="bottom">
                          <field name="length"/>
                          <field name="width"/>
                          <field name="crosssectional_area"/>
                          <field name="wt_of_cement_cube"/>
                          <field name="crushing_load" />
                          <field name="compressive_strength" />
                        </tree>
                      </field>
                      <field name="average_7days_slag_opc"/>
                    </group>

                    <!-- 28 days  -->
                    <group attrs="{'invisible': [('slag_activity_visible', '=', False)]}">
                        <h1>
                            <field name="casting_28_name_opc" readonly="1" nolabel="1"/>

                            <!-- <field name="dry_sieving_visible" invisible="1"/> -->
                        </h1>
                    </group>
                    <group attrs="{'invisible': [('slag_activity_visible', '=', False)]}">
                            <field name="status_28days_opc"/>
                      
                    </group>
                    
                    <group attrs="{'invisible': [('slag_activity_visible', '=', False)]}">


                      <field name="casting_date_28days_opc"/>
                      <field name="testing_date_28days_opc"/>
                      
                      <field name="slag_28days_table_opc">
                        <tree editable="bottom">
                          <field name="length"/>
                          <field name="width"/>
                          <field name="crosssectional_area"/>
                          <field name="wt_of_cement_cube"/>
                          <field name="crushing_load" />
                          <field name="compressive_strength" />
                        </tree>
                      </field>
                      <field name="average_28days_slag_opc"/>
                    </group>
                    <group attrs="{'invisible': [('slag_activity_visible', '=', False)]}">
                      <field name="slag_activity_index_7days"/>
                      <field name="slag_activity_index_28days"/>

                    </group>

                    <!-- Fineness  -->

                    <group attrs="{'invisible': [('fineness_visible', '=', False)]}">
                        <h1>
                            <field name="fineness_name" readonly="1" nolabel="1"/>
                            <field name="fineness_visible" invisible="1"/>
                        </h1>
                    </group>

                    <group attrs="{'invisible': [('fineness_visible', '=', False)]}">
                        <label for="weight_of_mercury_before_trial1" string="Weight of mercury before placing the sample in the permeability cell  (m₁),g."/>
                        <div class="address_format " >
                          <group colspan="1"  class="oe_inline">
                            <label for="weight_of_mercury_before_trial1" string="Trial 1" />
                            <field  name="weight_of_mercury_before_trial1"  colspan="3"  nolabel="1"/>
                          </group>
                          <group colspan="1" class="oe_inline"  >
                            <label for="weight_of_mercury_before_trial2" string="Trial 2" />
                            <field  name="weight_of_mercury_before_trial2"  colspan="3"  nolabel="1"/>
                          </group>
                        </div>
                    </group>
                    <group attrs="{'invisible': [('fineness_visible', '=', False)]}">
                        <label for="weight_of_mercury_after_trail1" string="Weight of mercury after palcing the sample in the permeability cell  (m₂),g." />
                        <div class="address_format " >
                          <group colspan="1"  class="oe_inline">
                            <label for="weight_of_mercury_after_trail1" string="" />
                            <field  name="weight_of_mercury_after_trail1"  colspan="3"  nolabel="1"/>
                          </group>
                          <group colspan="1" class="oe_inline"  >
                            <label for="weight_of_mercury_after_trail2" string="" />
                            <field  name="weight_of_mercury_after_trail2"  colspan="3"  nolabel="1"/>
                          </group>
                        </div>
                    </group>
                    <group attrs="{'invisible': [('fineness_visible', '=', False)]}">
                          <group>
                            <field  name="density_of_mercury"  colspan="6" />
                          </group>
                    </group>
                    <group attrs="{'invisible': [('fineness_visible', '=', False)]}">
                        <label for="bed_volume_trial1" string="Bed Volume (V=m₂-m₁/D),cm3." />
                        <div class="address_format " >
                          <group colspan="1"  class="oe_inline">
                            <label for="bed_volume_trial1" string="" />
                            <field  name="bed_volume_trial1"  colspan="3"  nolabel="1"/>
                          </group>
                          <group colspan="1" class="oe_inline"  >
                            <label for="bed_volume_trial2" string="" />
                            <field  name="bed_volume_trial2"  colspan="3"  nolabel="1"/>
                          </group>
                        </div>
                    </group>
                    <group attrs="{'invisible': [('fineness_visible', '=', False)]}">
                          <group>
                            <field  name="average_bed_volume"  colspan="6"/>
                          </group>
                    </group>
                    <group attrs="{'invisible': [('fineness_visible', '=', False)]}">                        
                          <group >
                            <field  name="difference_between_2_values"  colspan="6"/>
                          </group>
                    </group>
                    <group attrs="{'invisible': [('fineness_visible', '=', False)]}">
                      <h6>Repeat the procedure  with fresh cement beds until two values of V are obtained differing by less than 0.005 cm3.Record the mean of these two values as V</h6>
                    </group>
                    <group attrs="{'invisible': [('fineness_visible', '=', False)]}">
                      <h5>Determination of Apparatus Constant (k)</h5>
                    </group>
                    
                    <group attrs="{'invisible': [('fineness_visible', '=', False)]}">                        
                          <group >
                            <field  name="mass_of_sample_taken_fineness_reference"  colspan="6"/>
                          </group>
                    </group>
                    <group attrs="{'invisible': [('fineness_visible', '=', False)]}">
                      <h6>Take an amount (m1),g. of standard sample so as to give the sample bed of porosity e=0.500</h6>
                    </group>
                     <group attrs="{'invisible': [('fineness_visible', '=', False)]}">
                        <label for="time_fineness_trial1" string="Time(t),sec." />
                        <div class="address_format " >
                          <group colspan="1"  class="oe_inline">
                            <label for="time_fineness_trial1" string="1" />
                            <field  name="time_fineness_trial1"  colspan="3"  nolabel="1"/>
                          </group>
                          <group colspan="1" class="oe_inline"  >
                            <label for="time_fineness_trial2" string="2" />
                            <field  name="time_fineness_trial2"  colspan="3"  nolabel="1"/>
                          </group>
                          <group colspan="1" class="oe_inline"  >
                            <label for="time_fineness_trial3" string="3" />
                            <field  name="time_fineness_trial3"  colspan="3"  nolabel="1"/>
                          </group>
                        </div>
                    </group>
                    <group attrs="{'invisible': [('fineness_visible', '=', False)]}">
                        <label for="temp_fineness_trial1" string="Temp °C" />
                        <div class="address_format " >
                          <group colspan="1"  class="oe_inline">
                            <label for="temp_fineness_trial1" string="1" />
                            <field  name="temp_fineness_trial1"  colspan="3"  nolabel="1"/>
                          </group>
                          <group colspan="1" class="oe_inline"  >
                            <label for="temp_fineness_trial2" string="2" />
                            <field  name="temp_fineness_trial2"  colspan="3"  nolabel="1"/>
                          </group>
                          <group colspan="1" class="oe_inline"  >
                            <label for="temp_fineness_trial3" string="3" />
                            <field  name="temp_fineness_trial3"  colspan="3"  nolabel="1"/>
                          </group>
                        </div>
                    </group>
                    <group attrs="{'invisible': [('fineness_visible', '=', False)]}">                        
                          <group >
                            <field  name="average_time_fineness"  colspan="6"/>
                          </group>
                    </group>
                    <group attrs="{'invisible': [('fineness_visible', '=', False)]}">                        
                          <field name="specific_surface_of_reference_sample"/>
                          <field name="air_viscosity_of_three_temp"/>
                          <field name="density_of_reference_sample"/>
                          <field name="mean_of_three_measured_times"/>
                          <field name="apparatus_constant"/>
                    </group>
                    <group attrs="{'invisible': [('fineness_visible', '=', False)]}">
                      <h6>Determination of fineness</h6>
                    </group>
                    <group attrs="{'invisible': [('fineness_visible', '=', False)]}">
                      <h6>*Using the sample whose fineness is to be calculated.</h6>
                    </group>
                    <group attrs="{'invisible': [('fineness_visible', '=', False)]}">
                          <group>
                            <field  name="sg_fineness_calculated"  colspan="6"/>
                          </group>
                    </group>
                    <group attrs="{'invisible': [('fineness_visible', '=', False)]}">                        
                          <group >
                            <field  name="mass_of_sample_taken_fineness_calculated"  colspan="6"/>
                          </group>
                    </group>
                    <group attrs="{'invisible': [('fineness_visible', '=', False)]}">
                        <label for="time_sample_trial1" string="Time(t),sec." />
                        <div class="address_format " >
                          <group colspan="1"  class="oe_inline">
                            <label for="time_sample_trial1" string="1" />
                            <field  name="time_sample_trial1"  colspan="3"  nolabel="1"/>
                          </group>
                          <group colspan="1" class="oe_inline"  >
                            <label for="time_sample_trial2" string="2" />
                            <field  name="time_sample_trial2"  colspan="3"  nolabel="1"/>
                          </group>
                          <group colspan="1" class="oe_inline"  >
                            <label for="time_sample_trial3" string="3" />
                            <field  name="time_sample_trial3"  colspan="3"  nolabel="1"/>
                          </group>
                        </div>
                    </group>
                    <group attrs="{'invisible': [('fineness_visible', '=', False)]}">
                        <label for="temp_fineness_calculated_trial1" string="Temp °C" />
                        <div class="address_format " >
                          <group colspan="1"  class="oe_inline">
                            <label for="temp_fineness_calculated_trial1" string="1" />
                            <field  name="temp_fineness_calculated_trial1"  colspan="3"  nolabel="1"/>
                          </group>
                          <group colspan="1" class="oe_inline"  >
                            <label for="temp_fineness_calculated_trial2" string="2" />
                            <field  name="temp_fineness_calculated_trial2"  colspan="3"  nolabel="1"/>
                          </group>
                          <group colspan="1" class="oe_inline"  >
                            <label for="temp_fineness_calculated_trial3" string="3" />
                            <field  name="temp_fineness_calculated_trial3"  colspan="3"  nolabel="1"/>
                          </group>
                        </div>
                    </group>
                    <group attrs="{'invisible': [('fineness_visible', '=', False)]}">                        
                          <group >
                            <field  name="average_sample_time"  colspan="6"/>
                            <field  name="fineness_of_sample"  colspan="6"/>
                            <field  name="fineness_air_permeability"  colspan="6"/>
                          </group>
                    </group>
                </sheet>
            </form>
        </field>
        </record>

    </data>
</odoo>